ongoing_process_state/__init__.py
ongoing_process_state/bpmn_model.py
ongoing_process_state/n_gram_index.py
ongoing_process_state/petri_net.py
ongoing_process_state/reachability_graph.py
ongoing_process_state/utils.py
ongoing_process_state-2.1.2.dist-info/LICENSE
ongoing_process_state-2.1.2.dist-info/METADATA
ongoing_process_state-2.1.2.dist-info/WHEEL
ongoing_process_state-2.1.2.dist-info/RECORD
