Metadata-Version: 2.3
Name: ongoing-process-state
Version: 2.1.2
Summary: Build the n-gram index of a BPMN/Petri net process model to compute the state of an ongoing case in constant time.
Author: David Chapela de la Campa
Author-email: david.chapela.delacampa@gmail.com
Requires-Python: >=3.9,<3.12
Classifier: Programming Language :: Python :: 3
Classifier: Programming Language :: Python :: 3.9
Classifier: Programming Language :: Python :: 3.10
Classifier: Programming Language :: Python :: 3.11
Requires-Dist: pix-framework (>=0.14.0,<0.15.0)
